biostoch/__init__.py
biostoch/__main__.py
biostoch/cle.py
biostoch/model.py
biostoch/ode.py
biostoch/ssa.py
biostoch/tau_leaping.py
biostoch/visualization.py
biostoch-0.0.6.dist-info/LICENSE
biostoch-0.0.6.dist-info/METADATA
biostoch-0.0.6.dist-info/WHEEL
biostoch-0.0.6.dist-info/top_level.txt
biostoch-0.0.6.dist-info/RECORD
